pdlog/__init__.py
pdlog/accessor.py
pdlog/logging.py
pdlog/string.py
pdlog-0.1.0.post0.dist-info/LICENSE
pdlog-0.1.0.post0.dist-info/METADATA
pdlog-0.1.0.post0.dist-info/WHEEL
pdlog-0.1.0.post0.dist-info/top_level.txt
pdlog-0.1.0.post0.dist-info/RECORD
