Metadata-Version: 2.1
Name: pdlog
Version: 0.1.0.post0
Summary: Logging for pandas dataframes
Home-page: https://github.com/DataProphet/pdlog
Author: Wasim Lorgat
Author-email: wasim@dataprophet.com
License: MIT
Platform: UNKNOWN
Classifier: License :: OSI Approved :: MIT License
Classifier: Programming Language :: Python :: 3
Classifier: Programming Language :: Python :: 3 :: Only
Classifier: Programming Language :: Python :: 3.6
Classifier: Programming Language :: Python :: 3.7
Classifier: Programming Language :: Python :: 3.8
Classifier: Programming Language :: Python :: Implementation :: CPython
Classifier: Programming Language :: Python :: Implementation :: PyPy
Requires-Python: >=3.6.1
Requires-Dist: pandas
